{
  "id": 670,
  "name": "submitReceipt_Verizon_QA_670",
  "description": "Verizon submitReceipt storeID 0004 return success",
  "requestId": 670,
  "responseId": 670,
  "responder": "Verizon",
  "setId": null,
  "userId": 19,
  "api": "submitReceipt",
  "environment": "QA",
  "dateCreated": "2016-09-26 20:29:19",
  "dateModified": null,
  "createdBy": "Dan",
  "modifiedBy": null,
  "request": {
    "id": 670,
    "method": "POST",
    "url": "Amazon.com",
    "path": "/eai/eroes/VzwWSAdapter",
    "queryParameters": null,
    "xpath": true,
    "json": false,
    "pname1": "//*[local-name()='serviceAction' and text()='submitReceipt']",
    "pvalue1": null,
    "pname2": null,
    "pvalue2": null,
    "pname3": null,
    "pvalue3": null,
    "pname4": null,
    "pvalue4": null,
    "pname5": null,
    "pvalue5": null,
    "dateCreated": null,
    "dateModified": null,
    "createdBy": null,
    "modifiedBy": null,
    "asyncRequests": [],
    "cookies": [],
    "headers": []
  },
  "response": "${payload}",
  "user": {
    "id": 19,
    "type": "SDET",
    "name": "Dan",
    "dateCreated": "2016-06-15 21:17:36",
    "dateModified": null,
    "createdBy": "Dan",
    "modifiedBy": null
  },
  "retry": false,
  "retryTimes": null,
  "async": false,
  "expectationset": null
}